unitsafe/__init__.py
unitsafe/units.py
unitsafe-0.2.0.dist-info/LICENSE
unitsafe-0.2.0.dist-info/METADATA
unitsafe-0.2.0.dist-info/WHEEL
unitsafe-0.2.0.dist-info/RECORD
