Metadata-Version: 2.1
Name: unitsafe
Version: 0.2.0
Summary: A friendly way to handle engineering units in Python.
Home-page: https://github.com/jamesbayley/unitsafe.git
License: MIT
Author: James S. Bayley
Requires-Python: >=3.8
Classifier: Intended Audience :: Developers
Classifier: Intended Audience :: Education
Classifier: Intended Audience :: Science/Research
Classifier: License :: OSI Approved :: MIT License
Classifier: Operating System :: OS Independent
Classifier: Programming Language :: Python :: 3
Classifier: Programming Language :: Python :: 3.8
Classifier: Programming Language :: Python :: 3.9
Classifier: Programming Language :: Python :: 3.10
Classifier: Programming Language :: Python :: 3.11
Classifier: Programming Language :: Python :: 3.12
Classifier: Programming Language :: Python :: Implementation :: CPython
Classifier: Topic :: Scientific/Engineering
Project-URL: Repository, https://github.com/jamesbayley/unitsafe.git
